plivo/__init__.py
plivo/base.py
plivo/exceptions.py
plivo/version.py
plivo/resources/__init__.py
plivo/resources/accounts.py
plivo/resources/addresses.py
plivo/resources/applications.py
plivo/resources/brand.py
plivo/resources/call_feedback.py
plivo/resources/calls.py
plivo/resources/campaign.py
plivo/resources/conferences.py
plivo/resources/endpoints.py
plivo/resources/identities.py
plivo/resources/live_calls.py
plivo/resources/lookup.py
plivo/resources/maskingsession.py
plivo/resources/media.py
plivo/resources/messages.py
plivo/resources/multipartycall.py
plivo/resources/nodes.py
plivo/resources/numberpools.py
plivo/resources/numbers.py
plivo/resources/phlos.py
plivo/resources/powerpacks.py
plivo/resources/pricings.py
plivo/resources/profile.py
plivo/resources/queued_calls.py
plivo/resources/recordings.py
plivo/resources/regulatory_compliance.py
plivo/resources/token.py
plivo/resources/tollfree_verification.py
plivo/resources/transcription.py
plivo/resources/verify.py
plivo/resources/verify_callerid.py
plivo/rest/__init__.py
plivo/rest/base_client.py
plivo/rest/client.py
plivo/rest/phlo.py
plivo/rest/phlo_client.py
plivo/utils/__init__.py
plivo/utils/interactive.py
plivo/utils/jwt.py
plivo/utils/location.py
plivo/utils/signature_v3.py
plivo/utils/template.py
plivo/utils/validators.py
plivo/xml/ConferenceElement.py
plivo/xml/DTMFElement.py
plivo/xml/DialElement.py
plivo/xml/MultiPartyCallElement.py
plivo/xml/PlivoXMLElement.py
plivo/xml/ResponseElement.py
plivo/xml/__init__.py
plivo/xml/breakElement.py
plivo/xml/contElement.py
plivo/xml/emphasisElement.py
plivo/xml/getDigitsElement.py
plivo/xml/getInputElement.py
plivo/xml/hangupElement.py
plivo/xml/langElement.py
plivo/xml/messageElement.py
plivo/xml/numberElement.py
plivo/xml/pElement.py
plivo/xml/phonemeElement.py
plivo/xml/playElement.py
plivo/xml/preAnswerElement.py
plivo/xml/prosodyElement.py
plivo/xml/recordElement.py
plivo/xml/redirectElement.py
plivo/xml/sElement.py
plivo/xml/sayAsElement.py
plivo-4.59.5.dist-info/AUTHORS.md
plivo-4.59.5.dist-info/LICENSE.txt
plivo-4.59.5.dist-info/METADATA
plivo-4.59.5.dist-info/WHEEL
plivo-4.59.5.dist-info/top_level.txt
plivo-4.59.5.dist-info/RECORD
